arkenspy/__init__.py
arkenspy/__main__.py
Arkenspy-1.0.3.dist-info/LICENSE
Arkenspy-1.0.3.dist-info/METADATA
Arkenspy-1.0.3.dist-info/WHEEL
Arkenspy-1.0.3.dist-info/top_level.txt
Arkenspy-1.0.3.dist-info/RECORD
