Metadata-Version: 2.2
Name: Arkenspy
Version: 1.0.3
Summary: Arkenspy is a token manager library
Author: as2rofy
Author-email: a28092452@gmail.com
License: MIT
Project-URL: Source Repository, https://github.com/anigamer101/Arkens
License-File: LICENSE
Requires-Dist: github
Dynamic: author
Dynamic: author-email
Dynamic: description
Dynamic: description-content-type
Dynamic: license
Dynamic: project-url
Dynamic: requires-dist
Dynamic: summary
